<annotation>
	<folder>Panjabi-(1100-2101) Udayan</folder>
	<filename>1181.jpg</filename>
	<path>D:\project\Panjabi-(1100-2101) Udayan\1181.jpg</path>
	<source>
		<database>Unknown</database>
	</source>
	<size>
		<width>800</width>
		<height>374</height>
		<depth>3</depth>
	</size>
	<segmented>0</segmented>
	<object>
		<name>panjabi</name>
		<pose>Unspecified</pose>
		<truncated>0</truncated>
		<difficult>0</difficult>
		<bndbox>
			<xmin>126</xmin>
			<ymin>27</ymin>
			<xmax>297</xmax>
			<ymax>336</ymax>
		</bndbox>
	</object>
	<object>
		<name>panjabi</name>
		<pose>Unspecified</pose>
		<truncated>0</truncated>
		<difficult>0</difficult>
		<bndbox>
			<xmin>515</xmin>
			<ymin>27</ymin>
			<xmax>706</xmax>
			<ymax>341</ymax>
		</bndbox>
	</object>
</annotation>
