<annotation>
	<folder>t-shirt_jeans-(2200-3202) Fuad</folder>
	<filename>2333.jpg</filename>
	<path>G:\t-shirt_jeans-(2200-3202) Fuad\2333.jpg</path>
	<source>
		<database>Unknown</database>
	</source>
	<size>
		<width>342</width>
		<height>391</height>
		<depth>3</depth>
	</size>
	<segmented>0</segmented>
	<object>
		<name>t-shirt</name>
		<pose>Unspecified</pose>
		<truncated>0</truncated>
		<difficult>0</difficult>
		<bndbox>
			<xmin>7</xmin>
			<ymin>14</ymin>
			<xmax>330</xmax>
			<ymax>378</ymax>
		</bndbox>
	</object>
</annotation>
