<annotation>
	<folder>t-shirt_jeans-(2200-3202) Fuad</folder>
	<filename>2813.jpg</filename>
	<path>G:\t-shirt_jeans-(2200-3202) Fuad\2813.jpg</path>
	<source>
		<database>Unknown</database>
	</source>
	<size>
		<width>480</width>
		<height>693</height>
		<depth>3</depth>
	</size>
	<segmented>0</segmented>
	<object>
		<name>t-shirt</name>
		<pose>Unspecified</pose>
		<truncated>0</truncated>
		<difficult>0</difficult>
		<bndbox>
			<xmin>81</xmin>
			<ymin>159</ymin>
			<xmax>377</xmax>
			<ymax>589</ymax>
		</bndbox>
	</object>
	<object>
		<name>pant</name>
		<pose>Unspecified</pose>
		<truncated>0</truncated>
		<difficult>0</difficult>
		<bndbox>
			<xmin>105</xmin>
			<ymin>554</ymin>
			<xmax>369</xmax>
			<ymax>692</ymax>
		</bndbox>
	</object>
</annotation>
