<annotation>
	<folder>blazer_jacket-(4400-5402) Hridoy</folder>
	<filename>4703.jpg</filename>
	<path>F:\blazer_jacket-(4400-5402) Hridoy\4703.jpg</path>
	<source>
		<database>Unknown</database>
	</source>
	<size>
		<width>350</width>
		<height>704</height>
		<depth>3</depth>
	</size>
	<segmented>0</segmented>
	<object>
		<name>blazer</name>
		<pose>Unspecified</pose>
		<truncated>0</truncated>
		<difficult>0</difficult>
		<bndbox>
			<xmin>29</xmin>
			<ymin>149</ymin>
			<xmax>305</xmax>
			<ymax>593</ymax>
		</bndbox>
	</object>
</annotation>
