<annotation>
	<folder>blazer_jacket-(4400-5402) Hridoy</folder>
	<filename>5175.jpg</filename>
	<path>F:\blazer_jacket-(4400-5402) Hridoy\5175.jpg</path>
	<source>
		<database>Unknown</database>
	</source>
	<size>
		<width>480</width>
		<height>692</height>
		<depth>3</depth>
	</size>
	<segmented>0</segmented>
	<object>
		<name>blazer</name>
		<pose>Unspecified</pose>
		<truncated>0</truncated>
		<difficult>0</difficult>
		<bndbox>
			<xmin>93</xmin>
			<ymin>172</ymin>
			<xmax>406</xmax>
			<ymax>538</ymax>
		</bndbox>
	</object>
</annotation>
