<annotation>
	<folder>blazer_jacket-(4400-5402) Hridoy</folder>
	<filename>5284.jpg</filename>
	<path>F:\blazer_jacket-(4400-5402) Hridoy\5284.jpg</path>
	<source>
		<database>Unknown</database>
	</source>
	<size>
		<width>480</width>
		<height>480</height>
		<depth>3</depth>
	</size>
	<segmented>0</segmented>
	<object>
		<name>blazer</name>
		<pose>Unspecified</pose>
		<truncated>0</truncated>
		<difficult>0</difficult>
		<bndbox>
			<xmin>28</xmin>
			<ymin>4</ymin>
			<xmax>464</xmax>
			<ymax>478</ymax>
		</bndbox>
	</object>
</annotation>
