<annotation>
	<folder>blazer_jacket-(4400-5402) Hridoy</folder>
	<filename>5353.jpg</filename>
	<path>F:\blazer_jacket-(4400-5402) Hridoy\5353.jpg</path>
	<source>
		<database>Unknown</database>
	</source>
	<size>
		<width>850</width>
		<height>995</height>
		<depth>3</depth>
	</size>
	<segmented>0</segmented>
	<object>
		<name>blazer</name>
		<pose>Unspecified</pose>
		<truncated>0</truncated>
		<difficult>0</difficult>
		<bndbox>
			<xmin>179</xmin>
			<ymin>268</ymin>
			<xmax>692</xmax>
			<ymax>843</ymax>
		</bndbox>
	</object>
</annotation>
