<annotation>
	<folder>hijab(7000-)</folder>
	<filename>7024.jpg</filename>
	<path>F:\clean data f\hijab(7000-)\7024.jpg</path>
	<source>
		<database>Unknown</database>
	</source>
	<size>
		<width>320</width>
		<height>428</height>
		<depth>3</depth>
	</size>
	<segmented>0</segmented>
	<object>
		<name>hijab</name>
		<pose>Unspecified</pose>
		<truncated>1</truncated>
		<difficult>0</difficult>
		<bndbox>
			<xmin>28</xmin>
			<ymin>1</ymin>
			<xmax>182</xmax>
			<ymax>222</ymax>
		</bndbox>
	</object>
	<object>
		<name>hijab</name>
		<pose>Unspecified</pose>
		<truncated>0</truncated>
		<difficult>0</difficult>
		<bndbox>
			<xmin>8</xmin>
			<ymin>350</ymin>
			<xmax>35</xmax>
			<ymax>389</ymax>
		</bndbox>
	</object>
	<object>
		<name>hijab</name>
		<pose>Unspecified</pose>
		<truncated>0</truncated>
		<difficult>0</difficult>
		<bndbox>
			<xmin>56</xmin>
			<ymin>352</ymin>
			<xmax>80</xmax>
			<ymax>384</ymax>
		</bndbox>
	</object>
	<object>
		<name>hijab</name>
		<pose>Unspecified</pose>
		<truncated>0</truncated>
		<difficult>0</difficult>
		<bndbox>
			<xmin>102</xmin>
			<ymin>352</ymin>
			<xmax>125</xmax>
			<ymax>384</ymax>
		</bndbox>
	</object>
	<object>
		<name>hijab</name>
		<pose>Unspecified</pose>
		<truncated>0</truncated>
		<difficult>0</difficult>
		<bndbox>
			<xmin>143</xmin>
			<ymin>348</ymin>
			<xmax>176</xmax>
			<ymax>388</ymax>
		</bndbox>
	</object>
	<object>
		<name>hijab</name>
		<pose>Unspecified</pose>
		<truncated>0</truncated>
		<difficult>0</difficult>
		<bndbox>
			<xmin>186</xmin>
			<ymin>352</ymin>
			<xmax>222</xmax>
			<ymax>400</ymax>
		</bndbox>
	</object>
	<object>
		<name>hijab</name>
		<pose>Unspecified</pose>
		<truncated>0</truncated>
		<difficult>0</difficult>
		<bndbox>
			<xmin>235</xmin>
			<ymin>352</ymin>
			<xmax>265</xmax>
			<ymax>396</ymax>
		</bndbox>
	</object>
	<object>
		<name>hijab</name>
		<pose>Unspecified</pose>
		<truncated>0</truncated>
		<difficult>0</difficult>
		<bndbox>
			<xmin>286</xmin>
			<ymin>352</ymin>
			<xmax>310</xmax>
			<ymax>392</ymax>
		</bndbox>
	</object>
</annotation>
